event_journal/__init__.py
event_journal/database.py
event_journal/models.py
event_journal/standalone.py
event_journal/utils.py
event_journal-1.1.0.dist-info/licenses/LICENSE
event_journal-1.1.0.dist-info/METADATA
event_journal-1.1.0.dist-info/WHEEL
event_journal-1.1.0.dist-info/entry_points.txt
event_journal-1.1.0.dist-info/top_level.txt
event_journal-1.1.0.dist-info/RECORD
