Metadata-Version: 2.4
Name: event-journal
Version: 1.1.0
Summary: A simple Python library for logging events to PostgreSQL database
Home-page: https://github.com/amolsr/event_journal
Author: Amol Saini
Author-email: Amol Saini <amol.saini567@gmail.com>
License: MIT
Project-URL: Homepage, https://github.com/amolsr/event_journal
Project-URL: Documentation, https://github.com/amolsr/event_journal#readme
Project-URL: Repository, https://github.com/amolsr/event_journal
Project-URL: Bug Tracker, https://github.com/amolsr/event_journal/issues
Keywords: python,logging,events,postgresql,supabase,database,audit
Classifier: Development Status :: 4 - Beta
Classifier: Intended Audience :: Developers
Classifier: License :: OSI Approved :: MIT License
Classifier: Operating System :: OS Independent
Classifier: Programming Language :: Python :: 3
Classifier: Programming Language :: Python :: 3.8
Classifier: Programming Language :: Python :: 3.9
Classifier: Programming Language :: Python :: 3.10
Classifier: Programming Language :: Python :: 3.11
Classifier: Programming Language :: Python :: 3.12
Classifier: Topic :: Software Development :: Libraries :: Python Modules
Classifier: Topic :: System :: Logging
Classifier: Topic :: Database
Requires-Python: >=3.8
License-File: LICENSE
Requires-Dist: psycopg2-binary>=2.8.6
Provides-Extra: dev
Requires-Dist: pytest>=6.0; extra == "dev"
Requires-Dist: black>=22.0; extra == "dev"
Requires-Dist: flake8>=4.0; extra == "dev"
Requires-Dist: twine>=4.0; extra == "dev"
Requires-Dist: build>=0.10; extra == "dev"
Dynamic: author
Dynamic: home-page
Dynamic: license-file
Dynamic: requires-python
